agentiacap/agents/agentClassifier.py
agentiacap/agents/agentCleaner.py
agentiacap/agents/agente_sap.py
agentiacap/agents/agentExtractor.py
agentiacap/agents/responser.py
agentiacap/llms/llms.py
agentiacap/llms/Prompts.py
agentiacap/tools/busqueda_sap.py
agentiacap/tools/clean_resume(dev).py
agentiacap/tools/convert_pdf.py
agentiacap/tools/document_intelligence.py
agentiacap/tools/documents_classifier.py
agentiacap/tools/Ejemplos.json
agentiacap/tools/evaluate_context.py
agentiacap/tools/vision.py
agentiacap/utils/_actualizar_sociedades_activas(dev).py
agentiacap/utils/config.json
agentiacap/utils/descargar_blob.py
agentiacap/utils/globals.py
agentiacap/workflows/_sentiment_validator.py
agentiacap/workflows/desk(dev).py
agentiacap/workflows/devolucion_retenciones.py
agentiacap/workflows/estado_facturas.py
agentiacap/workflows/impresion_op.py
agentiacap/workflows/main.py
agentiacap-0.1.37.dist-info/METADATA
agentiacap-0.1.37.dist-info/WHEEL
agentiacap-0.1.37.dist-info/RECORD
