Metadata-Version: 2.3
Name: agentiacap
Version: 0.1.37
Summary: 
Author: Adrián Martínez
Author-email: amartinez@entaconsulting.com
Requires-Python: >=3.10.0,<4.0
Classifier: Programming Language :: Python :: 3
Classifier: Programming Language :: Python :: 3.10
Classifier: Programming Language :: Python :: 3.11
Classifier: Programming Language :: Python :: 3.12
Classifier: Programming Language :: Python :: 3.13
Requires-Dist: aiohappyeyeballs (==2.5.0)
Requires-Dist: aiohttp (==3.11.13)
Requires-Dist: aiosignal (==1.3.2)
Requires-Dist: annotated-types (==0.7.0)
Requires-Dist: anyio (==4.8.0)
Requires-Dist: async-timeout (==4.0.3)
Requires-Dist: attrs (==25.1.0)
Requires-Dist: azure-ai-documentintelligence (==1.0.0)
Requires-Dist: azure-ai-formrecognizer (==3.3.3)
Requires-Dist: azure-common (==1.1.28)
Requires-Dist: azure-core (==1.32.0)
Requires-Dist: azure-functions (==1.21.3)
Requires-Dist: azure-functions-durable (==1.2.10)
Requires-Dist: azure-identity (==1.20.0)
Requires-Dist: azure-storage-blob (==12.24.1)
Requires-Dist: certifi (==2025.1.31)
Requires-Dist: cffi (==1.17.1)
Requires-Dist: charset-normalizer (==3.4.1)
Requires-Dist: click (==8.1.8)
Requires-Dist: colorama (==0.4.6)
Requires-Dist: cryptography (==43.0.3)
Requires-Dist: dataclasses-json (==0.6.7)
Requires-Dist: distro (==1.9.0)
Requires-Dist: dotenv (>=0.9.9,<0.10.0)
Requires-Dist: et-xmlfile (==2.0.0)
Requires-Dist: exceptiongroup (==1.2.2)
Requires-Dist: fastapi (==0.115.11)
Requires-Dist: frozenlist (==1.5.0)
Requires-Dist: furl (==2.1.3)
Requires-Dist: greenlet (==3.1.1)
Requires-Dist: h11 (==0.14.0)
Requires-Dist: httpcore (==1.0.7)
Requires-Dist: httpx (==0.28.1)
Requires-Dist: httpx-sse (==0.4.0)
Requires-Dist: idna (==3.10)
Requires-Dist: isodate (==0.7.2)
Requires-Dist: jiter (==0.8.2)
Requires-Dist: jsonpatch (==1.33)
Requires-Dist: jsonpointer (==3.0.0)
Requires-Dist: langchain (==0.3.20)
Requires-Dist: langchain-community (==0.3.19)
Requires-Dist: langchain-core (==0.3.41)
Requires-Dist: langchain-openai (==0.3.7)
Requires-Dist: langchain-text-splitters (==0.3.6)
Requires-Dist: langgraph (==0.2.76)
Requires-Dist: langgraph-checkpoint (==2.0.16)
Requires-Dist: langgraph-cli (==0.1.74)
Requires-Dist: langgraph-sdk (==0.1.53)
Requires-Dist: langsmith (==0.3.11)
Requires-Dist: marshmallow (==3.26.1)
Requires-Dist: msal (==1.31.1)
Requires-Dist: msal-extensions (==1.2.0)
Requires-Dist: msgpack (==1.1.0)
Requires-Dist: msrest (==0.7.1)
Requires-Dist: multidict (==6.1.0)
Requires-Dist: mypy-extensions (==1.0.0)
Requires-Dist: numpy (==1.26.4)
Requires-Dist: oauthlib (==3.2.2)
Requires-Dist: openai (==1.65.4)
Requires-Dist: openpyxl (==3.1.5)
Requires-Dist: orderedmultidict (==1.0.1)
Requires-Dist: orjson (==3.10.15)
Requires-Dist: packaging (==24.2)
Requires-Dist: pandas (==2.2.3)
Requires-Dist: portalocker (==2.10.1)
Requires-Dist: propcache (==0.3.0)
Requires-Dist: pycparser (==2.22)
Requires-Dist: pydantic (==2.10.6)
Requires-Dist: pydantic-core (==2.27.2)
Requires-Dist: pydantic-settings (==2.8.1)
Requires-Dist: pyjwt (==2.10.1)
Requires-Dist: pymupdf (==1.25.3)
Requires-Dist: python-dateutil (==2.9.0.post0)
Requires-Dist: python-dotenv (==1.0.1)
Requires-Dist: python-multipart (==0.0.20)
Requires-Dist: pytz (==2025.1)
Requires-Dist: pyyaml (==6.0.2)
Requires-Dist: regex (==2024.11.6)
Requires-Dist: requests (==2.32.3)
Requires-Dist: requests-oauthlib (==2.0.0)
Requires-Dist: requests-toolbelt (==1.0.0)
Requires-Dist: six (==1.17.0)
Requires-Dist: sniffio (==1.3.1)
Requires-Dist: sqlalchemy (==2.0.38)
Requires-Dist: starlette (==0.46.0)
Requires-Dist: tenacity (==9.0.0)
Requires-Dist: tiktoken (==0.9.0)
Requires-Dist: tqdm (==4.67.1)
Requires-Dist: typing-extensions (==4.12.2)
Requires-Dist: typing-inspect (==0.9.0)
Requires-Dist: tzdata (==2025.1)
Requires-Dist: urllib3 (==2.3.0)
Requires-Dist: yarl (==1.18.3)
Requires-Dist: zstandard (==0.23.0)
